pyatv/__init__.py
pyatv/conf.py
pyatv/const.py
pyatv/convert.py
pyatv/exceptions.py
pyatv/helpers.py
pyatv/interface.py
pyatv/py.typed
pyatv/settings.py
pyatv/auth/hap_channel.py
pyatv/auth/hap_pairing.py
pyatv/auth/hap_session.py
pyatv/auth/hap_srp.py
pyatv/auth/hap_tlv8.py
pyatv/auth/server_auth.py
pyatv/core/__init__.py
pyatv/core/facade.py
pyatv/core/mdns.py
pyatv/core/protocol.py
pyatv/core/relayer.py
pyatv/core/scan.py
pyatv/protocols/__init__.py
pyatv/protocols/airplay/__init__.py
pyatv/protocols/airplay/ap2_session.py
pyatv/protocols/airplay/channels.py
pyatv/protocols/airplay/mrp_connection.py
pyatv/protocols/airplay/pairing.py
pyatv/protocols/airplay/player.py
pyatv/protocols/airplay/server_auth.py
pyatv/protocols/airplay/srp.py
pyatv/protocols/airplay/utils.py
pyatv/protocols/airplay/auth/__init__.py
pyatv/protocols/airplay/auth/hap.py
pyatv/protocols/airplay/auth/hap_transient.py
pyatv/protocols/airplay/auth/legacy.py
pyatv/protocols/companion/__init__.py
pyatv/protocols/companion/api.py
pyatv/protocols/companion/auth.py
pyatv/protocols/companion/connection.py
pyatv/protocols/companion/keyed_archiver.py
pyatv/protocols/companion/pairing.py
pyatv/protocols/companion/protocol.py
pyatv/protocols/companion/server_auth.py
pyatv/protocols/companion/plist_payloads/__init__.py
pyatv/protocols/companion/plist_payloads/rti_text_operations.py
pyatv/protocols/dmap/__init__.py
pyatv/protocols/dmap/daap.py
pyatv/protocols/dmap/pairing.py
pyatv/protocols/dmap/parser.py
pyatv/protocols/dmap/tag_definitions.py
pyatv/protocols/dmap/tags.py
pyatv/protocols/mrp/__init__.py
pyatv/protocols/mrp/auth.py
pyatv/protocols/mrp/connection.py
pyatv/protocols/mrp/messages.py
pyatv/protocols/mrp/pairing.py
pyatv/protocols/mrp/player_state.py
pyatv/protocols/mrp/protocol.py
pyatv/protocols/mrp/server_auth.py
pyatv/protocols/mrp/protobuf/AudioFadeMessage.proto
pyatv/protocols/mrp/protobuf/AudioFadeMessage_pb2.py
pyatv/protocols/mrp/protobuf/AudioFadeMessage_pb2.pyi
pyatv-0.15.1.dist-info/LICENSE.md
pyatv-0.15.1.dist-info/METADATA
pyatv-0.15.1.dist-info/WHEEL
pyatv-0.15.1.dist-info/entry_points.txt
pyatv-0.15.1.dist-info/top_level.txt
pyatv-0.15.1.dist-info/RECORD
