Metadata-Version: 2.1
Name: pyatv
Version: 0.15.1
Summary: A client library for Apple TV and AirPlay devices
Home-page: https://pyatv.dev
Download-URL: https://github.com/postlund/pyatv/archive/refs/tags/v0.15.1.zip
Author: Pierre Ståhl
Author-email: pierre.staahl@gmail.com
License: MIT
Project-URL: Repository, https://github.com/postlund/pyatv
Project-URL: Bug Reports, https://github.com/postlund/pyatv/issues
Keywords: apple,tv,airplay,raop,companion,dmap,dacp
Platform: any
Classifier: Development Status :: 4 - Beta
Classifier: Intended Audience :: Developers
Classifier: License :: OSI Approved :: MIT License
Classifier: Operating System :: OS Independent
Classifier: Programming Language :: Python :: 3.8
Classifier: Programming Language :: Python :: 3.9
Classifier: Programming Language :: Python :: 3.10
Classifier: Programming Language :: Python :: 3.11
Classifier: Programming Language :: Python :: 3.12
Classifier: Topic :: Software Development :: Libraries
Classifier: Topic :: Home Automation
Classifier: Typing :: Typed
Requires-Python: >=3.8.1
License-File: LICENSE.md
Requires-Dist: aiohttp<5,>=3.8.3
Requires-Dist: async-timeout>=4.0.2
Requires-Dist: cryptography>=43.0.0
Requires-Dist: chacha20poly1305-reuseable>=0.13.2
Requires-Dist: ifaddr>=0.1.7
Requires-Dist: mediafile>=0.8.1
Requires-Dist: miniaudio>=1.45
Requires-Dist: protobuf>=4.25.3
Requires-Dist: pydantic>=1.10.10
Requires-Dist: requests>=2.23.0
Requires-Dist: srptools>=0.2.0
Requires-Dist: tabulate>=0.9.0
Requires-Dist: zeroconf>=0.129.0
